djydoc/__init__.py
djydoc/management/commands/djydoc.py
djydoc-0.1.3.dev0.dist-info/LICENSE.md
djydoc-0.1.3.dev0.dist-info/WHEEL
djydoc-0.1.3.dev0.dist-info/METADATA
djydoc-0.1.3.dev0.dist-info/RECORD
