Metadata-Version: 2.1
Name: djydoc
Version: 0.1.3.dev0
Summary: Django wrapper for pydoc
Home-page: https://gitlab.com/srcrr/djydoc
License: MIT
Author: Jordan Hewitt
Author-email: srcrr@damngood.pro
Classifier: License :: OSI Approved :: MIT License
Classifier: Programming Language :: Python :: 2
Classifier: Programming Language :: Python :: 2.7
Classifier: Programming Language :: Python :: 3
Classifier: Programming Language :: Python :: 3.4
Classifier: Programming Language :: Python :: 3.5
Classifier: Programming Language :: Python :: 3.6
Classifier: Programming Language :: Python :: 3.7
Classifier: Programming Language :: Python :: 3.8
Requires-Dist: django (>=2.2.14,<3.0.0)
